<!--Copyright 2013 MLB Advanced Media, L.P.  Use of any content on this page acknowledges agreement to the terms posted here http://gdx.mlb.com/components/copyright.txt--><Player team="oak" id="452215" pos="C" current_position="DH" type="batter" first_name="Luke" last_name="Montz" jersey_number="22" height="6-1" weight="230" bats="R" throws="R" dob="07/07/1983"><season avg=".250" ab="4" h="1" bb="0" so="0" r="1" sb="0" cs="0" hr="0" rbi="1" ops=".750"/><career avg=".160" ab="25" h="4" bb="5" so="9" r="3" sb="0" cs="0" hr="1" rbi="4" ops=".620"/><month des="May" avg=".250" ab="4" h="1" bb="0" so="0" r="1" sb="0" cs="0" hr="0" rbi="1" ops=".750"/><Team des="Home" avg=".250" ab="4" h="1" bb="0" so="0" r="1" sb="0" cs="0" hr="0" rbi="1" ops=".750"/><Empty avg=".000" ab="0" h="0" bb="0" so="0" r="0" sb="0" cs="0" hr="0" rbi="0" ops=".000"/><Men_On avg=".250" ab="4" h="1" bb="0" so="0" r="1" sb="0" cs="0" hr="0" rbi="1" ops=".750"/><RISP avg=".000" ab="1" h="0" bb="0" so="0" r="1" sb="0" cs="0" hr="0" rbi="0" ops=".000"/><Loaded avg=".000" ab="0" h="0" bb="0" so="0" r="0" sb="0" cs="0" hr="0" rbi="0" ops=".000"/><vs_LHP avg=".250" ab="4" h="1" bb="0" so="0" r="1" sb="0" cs="0" hr="0" rbi="1" ops=".750"/><vs_RHP avg=".000" ab="0" h="0" bb="0" so="0" r="0" sb="0" cs="0" hr="0" rbi="0" ops=".000"/><vs_P des="Frieri" avg=".000" ab="0" h="0" bb="0" so="0" r="0" sb="0" cs="0" hr="0" rbi="0" ops=".000"/><vs_P5 des="Frieri" avg=".000" ab="0" h="0" bb="0" so="0" r="0" sb="0" cs="0" hr="0" rbi="0" ops=".000"/><Pitch loves="SI" hates="FF"/><faced><pitch type="FT"/><pitch type="CH"/><pitch type="SI"/><pitch type="FF"/></faced><atbats><ab inning="2" event="Flyout"/><ab inning="3" event="Pop Out"/><ab inning="6" event="Flyout"/><ab inning="8" event="Double"/></atbats></Player>